foliant/preprocessors/showcommits.py
foliantcontrib.showcommits-1.0.5.dist-info/LICENSE
foliantcontrib.showcommits-1.0.5.dist-info/METADATA
foliantcontrib.showcommits-1.0.5.dist-info/WHEEL
foliantcontrib.showcommits-1.0.5.dist-info/top_level.txt
foliantcontrib.showcommits-1.0.5.dist-info/RECORD
